{
  "components": [
    {
      "components": [
        {
          "components": [
            {
              "class": "col-md-12",
              "components": [
                {
                  "components": [
                    {
                      "components": [
                        {
                          "class": "col-md-3",
                          "components": [
                            {
                              "component": "FirstName",
                              "name": "FirstNameLabel",
                              "style": {
                                "width": "100%"
                              },
                              "text": "First Name",
                              "type": "label"
                            }
                          ],
                          "type": "col"
                        },
                        {
                          "class": "col-md-9",
                          "components": [
                            {
                              "maxLength": 50,
                              "name": "FirstName",
                              "style": {
                                "display": "block",
                                "width": "100%"
                              },
                              "type": "textbox"
                            },
                            {
                              "component": "FirstName",
                              "name": "FirstNameRequiredValidator",
                              "style": {
                                "position": "absolute"
                              },
                              "text": "FirstName is required",
                              "type": "required-validator"
                            }
                          ],
                          "type": "col"
                        }
                      ],
                      "style": {
                        "marginBottom": "1rem"
                      },
                      "type": "row"
                    },
                    {
                      "components": [
                        {
                          "class": "col-md-3",
                          "components": [
                            {
                              "component": "MiddleName",
                              "name": "MiddleNameLabel",
                              "style": {
                                "width": "100%"
                              },
                              "text": "Middle Name",
                              "type": "label"
                            }
                          ],
                          "type": "col"
                        },
                        {
                          "class": "col-md-9",
                          "components": [
                            {
                              "maxLength": 50,
                              "name": "MiddleName",
                              "style": {
                                "width": "100%"
                              },
                              "type": "textbox"
                            }
                          ],
                          "type": "col"
                        }
                      ],
                      "style": {
                        "marginBottom": "1rem"
                      },
                      "type": "row"
                    },
                    {
                      "components": [
                        {
                          "class": "col-md-3",
                          "components": [
                            {
                              "component": "Surname",
                              "name": "SurnameLabel",
                              "style": {
                                "width": "100%"
                              },
                              "text": "Surname",
                              "type": "label"
                            }
                          ],
                          "type": "col"
                        },
                        {
                          "class": "col-md-9",
                          "components": [
                            {
                              "maxLength": 50,
                              "name": "Surname",
                              "style": {
                                "display": "block",
                                "width": "100%"
                              },
                              "type": "textbox"
                            },
                            {
                              "component": "Surname",
                              "name": "SurnameRequiredValidator",
                              "style": {
                                "position": "absolute"
                              },
                              "text": "Surname is required",
                              "type": "required-validator"
                            }
                          ],
                          "type": "col"
                        }
                      ],
                      "style": {
                        "marginBottom": "1rem"
                      },
                      "type": "row"
                    },
                    {
                      "components": [
                        {
                          "class": "col-md-3",
                          "components": [
                            {
                              "component": "GenderID",
                              "name": "GenderIDLabel",
                              "style": {
                                "width": "100%"
                              },
                              "text": "Gender",
                              "type": "label"
                            }
                          ],
                          "type": "col"
                        },
                        {
                          "class": "col-md-9",
                          "components": [
                            {
                              "allowClear": true,
                              "allowFiltering": true,
                              "data": "${getGendersResult}",
                              "emptyFilterText": "No results found",
                              "multipleItemsSelectedText": "{0} items selected",
                              "name": "GenderID",
                              "placeholder": "Choose Gender",
                              "style": {
                                "display": "block",
                                "width": "100%"
                              },
                              "textProperty": "GenderName",
                              "type": "dropdown",
                              "valueProperty": "GenderID"
                            },
                            {
                              "component": "GenderID",
                              "name": "GenderIDRequiredValidator",
                              "style": {
                                "position": "absolute"
                              },
                              "text": "Gender is required",
                              "type": "required-validator"
                            }
                          ],
                          "type": "col"
                        }
                      ],
                      "style": {
                        "marginBottom": "1rem"
                      },
                      "type": "row"
                    },
                    {
                      "components": [
                        {
                          "class": "col-md-3",
                          "components": [
                            {
                              "component": "DateOfBirth",
                              "name": "DateOfBirthLabel",
                              "style": {
                                "width": "100%"
                              },
                              "text": "Date Of Birth",
                              "type": "label"
                            }
                          ],
                          "type": "col"
                        },
                        {
                          "class": "col-md-9",
                          "components": [
                            {
                              "name": "DateOfBirth",
                              "style": {
                                "width": "100%"
                              },
                              "type": "datepicker"
                            }
                          ],
                          "type": "col"
                        }
                      ],
                      "style": {
                        "marginBottom": "1rem"
                      },
                      "type": "row"
                    },
                    {
                      "components": [
                        {
                          "class": "col-md-3",
                          "components": [
                            {
                              "component": "ResidentialAddress",
                              "name": "ResidentialAddressLabel",
                              "style": {
                                "width": "100%"
                              },
                              "text": "Residential Address",
                              "type": "label"
                            }
                          ],
                          "type": "col"
                        },
                        {
                          "class": "col-md-9",
                          "components": [
                            {
                              "name": "ResidentialAddress",
                              "style": {
                                "display": "block",
                                "width": "100%"
                              },
                              "type": "textbox"
                            },
                            {
                              "component": "ResidentialAddress",
                              "name": "ResidentialAddressRequiredValidator",
                              "style": {
                                "position": "absolute"
                              },
                              "text": "ResidentialAddress is required",
                              "type": "required-validator"
                            }
                          ],
                          "type": "col"
                        }
                      ],
                      "style": {
                        "marginBottom": "1rem"
                      },
                      "type": "row"
                    },
                    {
                      "components": [
                        {
                          "class": "col-md-3",
                          "components": [
                            {
                              "component": "OfficeAddress",
                              "name": "OfficeAddressLabel",
                              "style": {
                                "width": "100%"
                              },
                              "text": "Office Address",
                              "type": "label"
                            }
                          ],
                          "type": "col"
                        },
                        {
                          "class": "col-md-9",
                          "components": [
                            {
                              "name": "OfficeAddress",
                              "style": {
                                "width": "100%"
                              },
                              "type": "textbox"
                            }
                          ],
                          "type": "col"
                        }
                      ],
                      "style": {
                        "marginBottom": "1rem"
                      },
                      "type": "row"
                    },
                    {
                      "components": [
                        {
                          "class": "col-md-3",
                          "components": [
                            {
                              "component": "MobileNumber1",
                              "name": "MobileNumber1Label",
                              "style": {
                                "width": "100%"
                              },
                              "text": "Mobile Number 1",
                              "type": "label"
                            }
                          ],
                          "type": "col"
                        },
                        {
                          "class": "col-md-9",
                          "components": [
                            {
                              "maxLength": 50,
                              "name": "MobileNumber1",
                              "style": {
                                "display": "block",
                                "width": "100%"
                              },
                              "type": "textbox"
                            },
                            {
                              "component": "MobileNumber1",
                              "name": "MobileNumber1RequiredValidator",
                              "style": {
                                "position": "absolute"
                              },
                              "text": "MobileNumber1 is required",
                              "type": "required-validator"
                            }
                          ],
                          "type": "col"
                        }
                      ],
                      "style": {
                        "marginBottom": "1rem"
                      },
                      "type": "row"
                    },
                    {
                      "components": [
                        {
                          "class": "col-md-3",
                          "components": [
                            {
                              "component": "WhatsappNumber",
                              "name": "WhatsappNumberLabel",
                              "style": {
                                "width": "100%"
                              },
                              "text": "Whatsapp Number",
                              "type": "label"
                            }
                          ],
                          "type": "col"
                        },
                        {
                          "class": "col-md-9",
                          "components": [
                            {
                              "maxLength": 50,
                              "name": "WhatsappNumber",
                              "style": {
                                "width": "100%"
                              },
                              "type": "textbox"
                            }
                          ],
                          "type": "col"
                        }
                      ],
                      "style": {
                        "marginBottom": "1rem"
                      },
                      "type": "row"
                    },
                    {
                      "components": [
                        {
                          "class": "col-md-3",
                          "components": [
                            {
                              "component": "Email",
                              "name": "EmailLabel",
                              "style": {
                                "width": "100%"
                              },
                              "text": "Email",
                              "type": "label"
                            }
                          ],
                          "type": "col"
                        },
                        {
                          "class": "col-md-9",
                          "components": [
                            {
                              "maxLength": 50,
                              "name": "Email",
                              "style": {
                                "width": "100%"
                              },
                              "type": "textbox"
                            },
                            {
                              "component": "Email",
                              "name": "emailValidator0",
                              "text": "Enter valid email",
                              "type": "email-validator"
                            }
                          ],
                          "type": "col"
                        }
                      ],
                      "style": {
                        "marginBottom": "1rem"
                      },
                      "type": "row"
                    },
                    {
                      "components": [
                        {
                          "class": "col-md-3",
                          "components": [
                            {
                              "component": "MemberPhoto",
                              "name": "MemberPhotoLabel",
                              "style": {
                                "width": "100%"
                              },
                              "text": "Member Photo",
                              "type": "label"
                            }
                          ],
                          "type": "col"
                        },
                        {
                          "class": "col-md-9",
                          "components": [
                            {
                              "name": "MemberPhoto",
                              "type": "file-input",
                              "value": "",
                              "chooseText": "Choose"
                            }
                          ],
                          "type": "col"
                        }
                      ],
                      "style": {
                        "marginBottom": "1rem"
                      },
                      "type": "row"
                    },
                    {
                      "components": [
                        {
                          "class": "col-md-3",
                          "components": [
                            {
                              "component": "CurrentPositionID",
                              "name": "CurrentPositionIDLabel",
                              "style": {
                                "width": "100%"
                              },
                              "text": "Member Position",
                              "type": "label"
                            }
                          ],
                          "type": "col"
                        },
                        {
                          "class": "col-md-9",
                          "components": [
                            {
                              "allowClear": true,
                              "allowFiltering": true,
                              "data": "${getMemberPositionsResult}",
                              "emptyFilterText": "No results found",
                              "multipleItemsSelectedText": "{0} items selected",
                              "name": "CurrentPositionID",
                              "placeholder": "Choose Position",
                              "style": {
                                "width": "100%"
                              },
                              "textProperty": "PositionName",
                              "type": "dropdown",
                              "valueProperty": "PositionID"
                            }
                          ],
                          "type": "col"
                        }
                      ],
                      "style": {
                        "marginBottom": "1rem"
                      },
                      "type": "row"
                    },
                    {
                      "components": [
                        {
                          "class": "col offset-sm-3",
                          "components": [
                            {
                              "buttonStyle": "primary",
                              "buttonType": "submit",
                              "icon": "save",
                              "text": "Save",
                              "type": "button"
                            },
                            {
                              "buttonStyle": "light",
                              "events": {
                                "click": [
                                  {
                                    "type": "back"
                                  }
                                ]
                              },
                              "style": {
                                "marginLeft": "1rem"
                              },
                              "text": "Cancel",
                              "type": "button"
                            }
                          ],
                          "type": "col"
                        }
                      ],
                      "type": "row"
                    }
                  ],
                  "events": {
                    "submit": [
                      {
                        "error": [
                          {
                            "detail": "Unable to create new Member!",
                            "severity": "error",
                            "summary": "Error",
                            "type": "notify"
                          }
                        ],
                        "name": "ConData.createMember",
                        "parameters": [
                          {
                            "name": "Member",
                            "value": "${event}"
                          }
                        ],
                        "then": [
                          {
                            "type": "back"
                          }
                        ],
                        "type": "invoke"
                      }
                    ]
                  },
                  "name": "form0",
                  "type": "template-form"
                }
              ],
              "type": "col"
            }
          ],
          "type": "row"
        }
      ],
      "container": "main",
      "type": "content"
    }
  ],
  "events": {
    "load": [
      {
        "name": "ConData.getGenders",
        "parameters": [],
        "then": [
          {
            "name": "getGendersResult",
            "type": "set",
            "value": "${result.value}"
          }
        ],
        "type": "invoke"
      },
      {
        "name": "ConData.getMemberPositions",
        "parameters": [],
        "then": [
          {
            "name": "getMemberPositionsResult",
            "type": "set",
            "value": "${result.value}"
          }
        ],
        "type": "invoke"
      }
    ]
  },
  "layout": "Main",
  "name": "Add Member",
  "access": [
    "Authenticated"
  ]
}